AUTHORS
LICENSE
MANIFEST.in
README
setup.py
dicom2cloud/__init__.py
dicom2cloud/clientgui.py
dicom2cloud/dicomviewer.py
dicom2cloud/dummydocker.py
dicom2cloud/noname.py
dicom2cloud/runDocker.py
dicom2cloud/uploadScripts.py
dicom2cloud.egg-info/PKG-INFO
dicom2cloud.egg-info/SOURCES.txt
dicom2cloud.egg-info/dependency_links.txt
dicom2cloud.egg-info/entry_points.txt
dicom2cloud.egg-info/requires.txt
dicom2cloud.egg-info/top_level.txt