Metadata-Version: 1.2
Name: dicom2cloud
Version: 0.9
Summary: Platform independent GUI for anonymizing/uploading brain scans to an image processing cloud instance
Home-page: https://github.com/CAIsr/dicom2cloud
Author: The Dicom2cloud Team
Author-email: steffen.bollmann@cai.uq.edu.au
License: BSD-2
Keywords: image processing mri
Platform: UNKNOWN
Classifier: Development Status :: 3 - Alpha
Classifier: Intended Audience :: Healthcare Industry
Classifier: Topic :: Scientific/Engineering :: Medical Science Apps.
Classifier: License :: OSI Approved :: BSD License
Classifier: Programming Language :: Python :: 2
Classifier: Programming Language :: Python :: 2.7
Requires-Python: ~=2.7
